hioso_ha7304/__init__.py
hioso_ha7304/ha7304.py
hioso_ha7304/mac.py
hioso_ha7304/onu.py
hioso_ha7304-0.8.2.dist-info/LICENSE
hioso_ha7304-0.8.2.dist-info/WHEEL
hioso_ha7304-0.8.2.dist-info/METADATA
hioso_ha7304-0.8.2.dist-info/RECORD
