Metadata-Version: 2.1
Name: hioso-ha7304
Version: 0.8.2
Summary: 
Author: hexatester
Author-email: hexatester@protonmail.com
Requires-Python: >=3.8,<4.0
Classifier: Programming Language :: Python :: 3
Classifier: Programming Language :: Python :: 3.10
Classifier: Programming Language :: Python :: 3.8
Classifier: Programming Language :: Python :: 3.9
Requires-Dist: attrs (>=21.0.0,<23.0.0)
Requires-Dist: cachetools (>=5.2.1,<6.0.0)
Requires-Dist: requests (>=2.28.0,<3.0.0)
